ALMAFE/__init__.py
ALMAFE/basic/EnumHelper.py
ALMAFE/basic/ParseTimeStamp.py
ALMAFE/basic/StripQuotes.py
ALMAFE/basic/Units.py
ALMAFE/basic/__init__.py
ALMAFE/common/GitVersion.py
ALMAFE/common/__init__.py
ALMAFE/database/DriverMySQL.py
ALMAFE/database/DriverOracle.py
ALMAFE/database/DriverSQLite.py
ALMAFE/database/__init__.py
ALMAFE/datastruct/NWayTree.py
ALMAFE/datastruct/__init__.py
ALMAFE/datastruct/test/__init__.py
ALMAFE/datastruct/test/t_NWayTree.py
ALMAFE/tests/__init__.py
ALMAFE_Lib-0.0.17.dist-info/LICENSE
ALMAFE_Lib-0.0.17.dist-info/METADATA
ALMAFE_Lib-0.0.17.dist-info/WHEEL
ALMAFE_Lib-0.0.17.dist-info/top_level.txt
ALMAFE_Lib-0.0.17.dist-info/RECORD
