Metadata-Version: 2.1
Name: ALMAFE-Lib
Version: 0.0.17
Summary: Contains reusable tools which are required by other ALMAFE packages.
Home-page: https://github.com/morganmcleod/ALMAFE-Lib
Author: Morgan McLeod
Author-email: mmcleod@nrao.edu
Classifier: Programming Language :: Python :: 3
Classifier: License :: OSI Approved :: GNU Lesser General Public License v2 or later (LGPLv2+)
Classifier: Operating System :: OS Independent
Requires-Python: >=3.8
License-File: LICENSE
Requires-Dist: python-dateutil>=2.8.1
Requires-Dist: mysql-connector-python>=8.0.18
Provides-Extra: oracle
Requires-Dist: cx-oracle>=8.1.0; extra == "oracle"
